CBloomfilter.cpython-38-darwin.so
iron_man/__init__.py
iron_man/__version__.py
iron_man/c_bloomfilter.h
iron_man/py_bloomfilter.py
iron_man-1.0.3.dist-info/LICENSE
iron_man-1.0.3.dist-info/METADATA
iron_man-1.0.3.dist-info/WHEEL
iron_man-1.0.3.dist-info/top_level.txt
iron_man-1.0.3.dist-info/RECORD
