Metadata-Version: 2.1
Name: iron-man
Version: 1.0.3
Summary: C & Python Bloomfilter Based Memeroy || Redis .
Home-page: http://gitlab.nuist.pro:3000/aberstone/IronMan.git
Author: Aberstone
Author-email: aberstone.hk@gmail.com
License: MIT License
Platform: UNKNOWN
Classifier: Development Status :: 5 - Production/Stable
Classifier: Intended Audience :: Developers
Classifier: Natural Language :: English
Classifier: License :: OSI Approved :: MIT License
Classifier: Programming Language :: C
Classifier: Programming Language :: Cython
Classifier: Topic :: Software Development :: Libraries :: Python Modules
